server/__init__.py
server/const.py
server/jim.py
server/server.py
server/server_db.py
server_chat-0.0.1.dist-info/METADATA
server_chat-0.0.1.dist-info/WHEEL
server_chat-0.0.1.dist-info/top_level.txt
server_chat-0.0.1.dist-info/RECORD
