Metadata-Version: 2.1
Name: server-chat
Version: 0.0.1
Summary: Server 'Async chat' application
Home-page: UNKNOWN
Author: Sergey Karnaukhov
Author-email: s_karn_v@mail.ru
License: UNKNOWN
Platform: UNKNOWN
Requires-Dist: sqlalchemy
